Metadata-Version: 1.0
Name: skbinstaller
Version: 1.0
Summary: Standalon Kivy Buildozer installer
Home-page: UNKNOWN
Author: UNKNOWN
Author-email: dankis12a@gmail.com
License: UNKNOWN
Platform: UNKNOWN
